MANIFEST.in
README.rst
setup.py
filedata/__init__.py
filedata/config.py
filedata/file.py
filedata/html.py
filedata/image.py
filedata/pdf.py
filedata/retry.py
filedata/text.py
filedata/time.py
filedata/utils.py
filedata/video.py
filedata.egg-info/PKG-INFO
filedata.egg-info/SOURCES.txt
filedata.egg-info/dependency_links.txt
filedata.egg-info/not-zip-safe
filedata.egg-info/requires.txt
filedata.egg-info/top_level.txt
filedata/text_algo/__init__.py
filedata/text_algo/ac.py
requirements/test.txt
tests/__init__.py
tests/test_text_algo/__init__.py
tests/test_text_algo/test_ac.py